odoo/addons/purchase_order_product_attachment_mgmt/README.rst
odoo/addons/purchase_order_product_attachment_mgmt/__init__.py
odoo/addons/purchase_order_product_attachment_mgmt/__manifest__.py
odoo/addons/purchase_order_product_attachment_mgmt/i18n/es.po
odoo/addons/purchase_order_product_attachment_mgmt/i18n/it.po
odoo/addons/purchase_order_product_attachment_mgmt/i18n/purchase_order_product_attachment_mgmt.pot
odoo/addons/purchase_order_product_attachment_mgmt/models/__init__.py
odoo/addons/purchase_order_product_attachment_mgmt/models/purchase_order.py
odoo/addons/purchase_order_product_attachment_mgmt/readme/CONTRIBUTORS.rst
odoo/addons/purchase_order_product_attachment_mgmt/readme/DESCRIPTION.rst
odoo/addons/purchase_order_product_attachment_mgmt/readme/USAGE.rst
odoo/addons/purchase_order_product_attachment_mgmt/static/description/icon.png
odoo/addons/purchase_order_product_attachment_mgmt/static/description/index.html
odoo/addons/purchase_order_product_attachment_mgmt/tests/__init__.py
odoo/addons/purchase_order_product_attachment_mgmt/tests/test_purchase_order_product_attachment_mgmt.py
odoo/addons/purchase_order_product_attachment_mgmt/views/purchase_order_view.xml
odoo_addon_purchase_order_product_attachment_mgmt-16.0.1.0.0.5.dist-info/METADATA
odoo_addon_purchase_order_product_attachment_mgmt-16.0.1.0.0.5.dist-info/WHEEL
odoo_addon_purchase_order_product_attachment_mgmt-16.0.1.0.0.5.dist-info/top_level.txt
odoo_addon_purchase_order_product_attachment_mgmt-16.0.1.0.0.5.dist-info/RECORD
